ADDPIO.py
LICENSE.txt
MANIFEST.in
README.rst
setup.cfg
setup.py
testADDPIO.py
ADDPIO.egg-info/PKG-INFO
ADDPIO.egg-info/SOURCES.txt
ADDPIO.egg-info/dependency_links.txt
ADDPIO.egg-info/top_level.txt