Metadata-Version: 1.1
Name: ADDPIO
Version: 1.0.3b1
Summary: Android IO project
Home-page: UNKNOWN
Author: Sipenlatt
Author-email: sipenlatt@gmail.com
License: MIT
Keywords: GPIO Android Raspberry Pi sensors IO
Platform: UNKNOWN
Classifier: Development Status :: 4 - Beta
Classifier: Intended Audience :: Developers
Classifier: Topic :: Software Development :: Build Tools
Classifier: License :: OSI Approved :: MIT License
Classifier: Programming Language :: Python :: 2
Classifier: Programming Language :: Python :: 2.6
Classifier: Programming Language :: Python :: 2.7
Classifier: Programming Language :: Python :: 3
Classifier: Programming Language :: Python :: 3.3
Classifier: Programming Language :: Python :: 3.4
Classifier: Programming Language :: Python :: 3.5
